saimll/__init__.py
saimll/pprint.py
saimll/logger/LogLevel.py
saimll/logger/__init__.py
saimll/logger/encoding.py
saimll/logger/log.py
saimll/saiml/__init__.py
saimll/saiml/color/__init__.py
saimll/saiml/color/colors.py
saimll/saiml/color/xterm_colors.py
saimll/saiml/markup/__init__.py
saimll/saiml/markup/formatting.py
saimll/saiml/markup/markup.py
saimll/saiml/markup/tokens.py
saimll-0.5.1.dist-info/METADATA
saimll-0.5.1.dist-info/WHEEL
saimll-0.5.1.dist-info/licenses/LICENSE
saimll-0.5.1.dist-info/RECORD
